[
    {
        "patient_id":"06492644",
        "core":4,
        "penumbra":189,
        "tdc_artery_peak":120,
        "tdc_artery_time":16,
        "tdc_vein_peak":380,
        "tdc_vein_time":24
    },
    {
        "patient_id":"0009065600",
        "core":0,
        "penumbra":0,
        "tdc_artery_peak":480,
        "tdc_artery_time":18,
        "tdc_vein_peak":720,
        "tdc_vein_time":24
    },
    {
        "patient_id":"0007411236",
        "core":0,
        "penumbra":93,
        "tdc_artery_peak":200,
        "tdc_artery_time":15,
        "tdc_vein_peak":500,
        "tdc_vein_time":18
    },
    {
        "patient_id":"M01513211",
        "core":0,
        "penumbra":19,
        "tdc_artery_peak":440,
        "tdc_artery_time":14,
        "tdc_vein_peak":560,
        "tdc_vein_time":18
    },
    {
        "patient_id":"V17593952",
        "core":0,
        "penumbra":0,
        "tdc_artery_peak":360,
        "tdc_artery_time":20,
        "tdc_vein_peak":600,
        "tdc_vein_time":24
    },
    {
        "patient_id":"P08693835",
        "core":0,
        "penumbra":105,
        "tdc_artery_peak":280,
        "tdc_artery_time":14,
        "tdc_vein_peak":420,
        "tdc_vein_time":24
    },
    {
        "patient_id":"K04419066",
        "core":0,
        "penumbra":0,
        "tdc_artery_peak":340,
        "tdc_artery_time":22,
        "tdc_vein_peak":460,
        "tdc_vein_time":32
    },
    {
        "patient_id":"2324353",
        "core":0,
        "penumbra":60,
        "tdc_artery_peak":280,
        "tdc_artery_time":21,
        "tdc_vein_peak":460,
        "tdc_vein_time":28
    },
    {
        "patient_id":"0007400446",
        "core":21,
        "penumbra":82,
        "tdc_artery_peak":260,
        "tdc_artery_time":18,
        "tdc_vein_peak":500,
        "tdc_vein_time":28
    },
    {
        "patient_id":"0009092567",
        "core":167,
        "penumbra":146,
        "tdc_artery_peak":220,
        "tdc_artery_time":18,
        "tdc_vein_peak":520,
        "tdc_vein_time":24
    },
    {
        "patient_id":"0008248086",
        "core":0,
        "penumbra":305,
        "tdc_artery_peak":380,
        "tdc_artery_time":18,
        "tdc_vein_peak":540,
        "tdc_vein_time":25
    },
    {
        "patient_id":"0004421313",
        "core":24,
        "penumbra":64,
        "tdc_artery_peak":500,
        "tdc_artery_time":20,
        "tdc_vein_peak":800,
        "tdc_vein_time":28
    },
    {
        "patient_id":"0009084147",
        "core":6,
        "penumbra":68,
        "tdc_artery_peak":320,
        "tdc_artery_time":27,
        "tdc_vein_peak":520,
        "tdc_vein_time":35
    },
    {
        "patient_id":"D00492898",
        "core":15,
        "penumbra":352,
        "tdc_artery_peak":320,
        "tdc_artery_time":12,
        "tdc_vein_peak":540,
        "tdc_vein_time":20
    },
    {
        "patient_id":"06417248",
        "core":0,
        "penumbra":0,
        "tdc_artery_peak":0,
        "tdc_artery_time":0,
        "tdc_vein_peak":0,
        "tdc_vein_time":0
    },
    {
        "patient_id":"06240201",
        "core":0,
        "penumbra":0,
        "tdc_artery_peak":0,
        "tdc_artery_time":0,
        "tdc_vein_peak":0,
        "tdc_vein_time":0
    },
    {
        "patient_id":"0007582662",
        "core":0,
        "penumbra":106,
        "tdc_artery_peak":0,
        "tdc_artery_time":0,
        "tdc_vein_peak":0,
        "tdc_vein_time":0
    },
    {
        "patient_id":"0002950581",
        "core":58,
        "penumbra":111,
        "tdc_artery_peak":0,
        "tdc_artery_time":0,
        "tdc_vein_peak":0,
        "tdc_vein_time":0
    },
    {
        "patient_id":"0008691167",
        "core":132,
        "penumbra":278,
        "tdc_artery_peak":0,
        "tdc_artery_time":0,
        "tdc_vein_peak":0,
        "tdc_vein_time":0
    },
    {
        "patient_id":"1447794",
        "core":21,
        "penumbra":138,
        "tdc_artery_peak":0,
        "tdc_artery_time":0,
        "tdc_vein_peak":0,
        "tdc_vein_time":0
    },
    {
        "patient_id":"2273202",
        "core":0,
        "penumbra":82,
        "tdc_artery_peak":0,
        "tdc_artery_time":0,
        "tdc_vein_peak":0,
        "tdc_vein_time":0
    },
    {
        "patient_id":"0008708244",
        "core":5,
        "penumbra":87,
        "tdc_artery_peak":0,
        "tdc_artery_time":0,
        "tdc_vein_peak":0,
        "tdc_vein_time":0
    },
    {
        "patient_id":"0004280572",
        "core":11,
        "penumbra":48,
        "tdc_artery_peak":0,
        "tdc_artery_time":0,
        "tdc_vein_peak":0,
        "tdc_vein_time":0
    },
    {
        "patient_id":"0008690650",
        "core":14,
        "penumbra":255,
        "tdc_artery_peak":0,
        "tdc_artery_time":0,
        "tdc_vein_peak":0,
        "tdc_vein_time":0
    },
    {
        "patient_id":"0008683445",
        "core":0,
        "penumbra":105,
        "tdc_artery_peak":0,
        "tdc_artery_time":0,
        "tdc_vein_peak":0,
        "tdc_vein_time":0
    },
    {
        "patient_id":"0008706584",
        "core":0,
        "penumbra":203,
        "tdc_artery_peak":0,
        "tdc_artery_time":0,
        "tdc_vein_peak":0,
        "tdc_vein_time":0
    }
]